{
  "response": [
    {
      "maintainer": "Achille (0xSharkBoy)",
      "oem": "Samsung",
      "device": "Galaxy S10",
      "filename": "EvolutionX-14.0-20240913-beyond1lte-v9.4-Official.zip",
      "download": "https://sourceforge.net/projects/evolution-x/files/beyond1lte/14/EvolutionX-14.0-20240913-beyond1lte-v9.4-Official.zip/download",
      "timestamp": "1726238250",
      "md5": "024de767ac6f403146695b9b6f8708c6",
      "sha256": "b4ccaf66dd9a01d9e54709e13da664a525f604e38c8855dd590bcc7adc49708f",
      "size": "2589879950",
      "version": "9.4",
      "buildtype": "Monthly",
      "forum": "https://xdaforums.com/t/rom-official-14-evolutionx-8-x-aosp-encryption.4669084/",
      "firmware": "",
      "paypal": "https://ko-fi.com/0xsharkboy",
      "telegram": "https://t.me/EvolutionXexynos982x"
    }
  ]
}
