{
  "response": [
    {
      "maintainer": "Achille (0xSharkBoy)",
      "oem": "Samsung",
      "device": "Galaxy F62",
      "filename": "EvolutionX-14.0-20240919-f62-v9.4-Official.zip",
      "download": "https://sourceforge.net/projects/evolution-x/files/f62/14/EvolutionX-14.0-20240919-f62-v9.4-Official.zip/download",
      "timestamp": "1726742940",
      "md5": "27235afc271f9becef66e11c93b4606f",
      "sha256": "e31c66d209c86ddd86ad2121a256a1bb22150fdcb2cebebafdc5b66e3de5e5af",
      "size": "2461413548",
      "version": "9.4",
      "buildtype": "Monthly",
      "forum": "https://xdaforums.com/t/rom-official-14-evolutionx-8-x-aosp-encryption.4669082/",
      "firmware": "",
      "paypal": "https://ko-fi.com/0xsharkboy",
      "telegram": "https://t.me/EvolutionXexynos982x",
      "github": "0xsharkboy",
      "initial_installation_images": [
        "recovery"
      ]
    }
  ]
}
