{
  "response": [
    {
      "maintainer": "Tejas Singh",
      "oem": "Xiaomi",
      "device": "Redmi Note 8/8T",
      "filename": "EvolutionX-14.0-20240811-ginkgo-v9.3-Official.zip",
      "download": "https://sourceforge.net/projects/evolution-x/files/ginkgo/14/EvolutionX-14.0-20240811-ginkgo-v9.3-Official.zip/download",
      "timestamp": 1723395329,
      "md5": "5ec1b094ba8dfa8be339f1ebcffea3e8",
      "sha256": "204abc3cc335816ddaf534dc45249cb38c3f479f04bcec1d821431aa3411146b",
      "size": 2062747516,
      "version": "9.3",
      "buildtype": "Release",
      "forum": "https://xdaforums.com/t/rom-14-official-unified-evolution-x-for-redmi-note-8-8t.4639684/",
      "firmware": "",
      "paypal": "https://paypal.me/tejas101k",
      "telegram": "https://t.me/tejas101k"
    }
  ]
}
