{
  "response": [
    {
      "maintainer": "ARIJIT SAHA",
      "oem": "Redmi",
      "device": "Redmi Note 12 5G/Poco X5 5G",
      "filename": "EvolutionX-14.0-20240821-stone-v9.3-Official.zip",
      "download": "https://sourceforge.net/projects/evolution-x/files/stone/14/EvolutionX-14.0-20240821-stone-v9.3-Official.zip/download",
      "timestamp": 1724220900,
      "md5": "b537944837539179dccbd1ed7c6e7ae0",
      "sha256": "1d8a5df85c5cb819190586d86607149f58f0fcc428cfe9ff74e0ac4ef953c1a5",
      "size": 2184594775,
      "version": "9.3",
      "buildtype": "Monthly",
      "forum": "https://xdaforums.com/t/rom-stone-official-evolution-xyz-9-3-08-21-2024.4688036/",
      "firmware": "",
      "paypal": "https://linktr.ee/joeyhuab",
      "telegram": "",
      "github": "arijit78",
      "initial_installation_images": [
        "boot"
      ]
    }
  ]
}
