{
  "response": [
    {
      "maintainer": "Joey Huab",
      "oem": "Xiaomi",
      "device": "Mi 11",
      "filename": "EvolutionX-14.0-20240917-venus-v9.4-Official.zip",
      "download": "https://sourceforge.net/projects/evolution-x/files/venus/14/EvolutionX-14.0-20240917-venus-v9.4-Official.zip/download",
      "timestamp": 1726585588,
      "md5": "8b1d688e4a5f90b198c00b3bce0c11f8",
      "sha256": "b8a0a028739266d57c21628f8e5df95eb9da502f3f5b604a5221ef540247c144",
      "size": 2812701022,
      "version": "9.4",
      "buildtype": "Release",
      "forum": "https://xdaforums.com/t/rom-14-0_r35-venus-official-evolution-x-05-09-24.4636519/",
      "firmware": "https://xmfirmwareupdater.com/firmware/venus/stable/OS1.0.6.0.UKBMIXM/",
      "paypal": "https://linktr.ee/joeyhuab",
      "telegram": ""
    }
  ]
}
